MANIFEST.in
README.rst
setup.py
django_b2storage/__init__.py
django_b2storage/backblaze_b2.py
django_b2storage/connectioninfo.py
django_b2storage.egg-info/PKG-INFO
django_b2storage.egg-info/SOURCES.txt
django_b2storage.egg-info/dependency_links.txt
django_b2storage.egg-info/not-zip-safe
django_b2storage.egg-info/requires.txt
django_b2storage.egg-info/top_level.txt